saml_ecp_demo/__init__.py
saml_ecp_demo/saml_ecp_demo.py
saml_ecp_demo-0.4.dist-info/METADATA
saml_ecp_demo-0.4.dist-info/RECORD
saml_ecp_demo-0.4.dist-info/WHEEL
saml_ecp_demo-0.4.dist-info/entry_points.txt
saml_ecp_demo-0.4.dist-info/top_level.txt
